{"last_update": "16/05/2025", "user_name": "Bong", "amount_spent_on_Food": 70000, "amount_spent_on_Home": 0, "amount_spent_on_Health": 0, "amount_spent_on_Work": 0, "amount_spent_on_Entertainment": 0, "amount_spent_on_Study": 0, "expected_expense_in_a_month": 670000, "recommended_amount_per_day": 22333, "recommended_amount_today": 22333, "your_expense": 70000, "expense_per_day_list": [50000, 20000], "total_expense_a_day": 70000, "left_amount_in_a_day": -47667, "total_left_amount": 600000, "expense_per_day_from_now_on": 20000}